plasTeX/Config.py
plasTeX/Context.py
plasTeX/Filenames.py
plasTeX/Logging.py
plasTeX/PackageResource.py
plasTeX/TeX.py
plasTeX/Tokenizer.py
plasTeX/__init__.py
plasTeX/encoding.py
plasTeX/i18n.xml
plasTeX/plasTeXrc
plasTeX/Base/__init__.py
plasTeX/Base/LaTeX/Accents.py
plasTeX/Base/LaTeX/Alignment.py
plasTeX/Base/LaTeX/Arrays.py
plasTeX/Base/LaTeX/Bibliography.py
plasTeX/Base/LaTeX/Boxes.py
plasTeX/Base/LaTeX/Breaking.py
plasTeX/Base/LaTeX/Characters.py
plasTeX/Base/LaTeX/Crossref.py
plasTeX/Base/LaTeX/Declarations.py
plasTeX/Base/LaTeX/Definitions.py
plasTeX/Base/LaTeX/Document.py
plasTeX/Base/LaTeX/Entities.py
plasTeX/Base/LaTeX/Environments.py
plasTeX/Base/LaTeX/Files.py
plasTeX/Base/LaTeX/Floats.py
plasTeX/Base/LaTeX/FontSelection.py
plasTeX/Base/LaTeX/Footnotes.py
plasTeX/Base/LaTeX/Index.py
plasTeX/Base/LaTeX/Lengths.py
plasTeX/Base/LaTeX/Lists.py
plasTeX/Base/LaTeX/Math.py
plasTeX/Base/LaTeX/Numbering.py
plasTeX/Base/LaTeX/Packages.py
plasTeX/Base/LaTeX/Paragraphs.py
plasTeX/Base/LaTeX/Pictures.py
plasTeX/Base/LaTeX/Quotations.py
plasTeX/Base/LaTeX/Sectioning.py
plasTeX/Base/LaTeX/Sentences.py
plasTeX/Base/LaTeX/Space.py
plasTeX/Base/LaTeX/Tabbing.py
plasTeX/Base/LaTeX/Verbatim.py
plasTeX/Base/LaTeX/__init__.py
plasTeX/Base/LaTeX/allkeys.txt
plasTeX/Base/LaTeX/ent.xml
plasTeX/Base/LaTeX/pyuca.py
plasTeX/Base/TeX/Fonts.py
plasTeX/Base/TeX/Macros.py
plasTeX/Base/TeX/Parameters.py
plasTeX/Base/TeX/Primitives.py
plasTeX/Base/TeX/Registers.py
plasTeX/Base/TeX/Text.py
plasTeX/Base/TeX/__init__.py
plasTeX/ConfigManager/Boolean.py
plasTeX/ConfigManager/Compound.py
plasTeX/ConfigManager/Counted.py
plasTeX/ConfigManager/Directories.py
plasTeX/ConfigManager/Files.py
plasTeX/ConfigManager/Float.py
plasTeX/ConfigManager/Generic.py
plasTeX/ConfigManager/Integer.py
plasTeX/ConfigManager/Multi.py
plasTeX/ConfigManager/String.py
plasTeX/ConfigManager/__init__.py
plasTeX/DOM/__init__.py
plasTeX/Imagers/OSXCoreGraphics.py
plasTeX/Imagers/__init__.py
plasTeX_gerby-1.0.2.dist-info/LICENSE
plasTeX_gerby-1.0.2.dist-info/METADATA
plasTeX_gerby-1.0.2.dist-info/WHEEL
plasTeX_gerby-1.0.2.dist-info/top_level.txt
plasTeX_gerby-1.0.2.dist-info/RECORD
